pigconf/__init__.py
pigconf/mapper.py
pigconf-0.0.3.dist-info/LICENSE.txt
pigconf-0.0.3.dist-info/METADATA
pigconf-0.0.3.dist-info/WHEEL
pigconf-0.0.3.dist-info/top_level.txt
pigconf-0.0.3.dist-info/RECORD
