Metadata-Version: 2.1
Name: pigconf
Version: 0.0.3
Summary: A yaml config mapper to create static config classes.
Home-page: https://github.com/AnshumanRohella/pigconf
Author: Anshuman Rohella
Author-email: rohella.anshuman@gmail.com
License: UNKNOWN
Platform: UNKNOWN
Classifier: Programming Language :: Python :: 3.6
Classifier: Programming Language :: Python :: 3.7
Classifier: Operating System :: OS Independent
Classifier: License :: OSI Approved :: GNU General Public License (GPL)
Requires-Dist: PyYAML (>=5.4.1)
Provides-Extra: dev
Requires-Dist: check-manifest (>=0.46) ; extra == 'dev'
Requires-Dist: pytest (>=6.2.2) ; extra == 'dev'
